image_generation_fastmcp_server/__init__.py
image_generation_fastmcp_server/__main__.py
image_generation_fastmcp_server/server.py
image_generation_fastmcp_server-0.1.1.dist-info/METADATA
image_generation_fastmcp_server-0.1.1.dist-info/WHEEL
image_generation_fastmcp_server-0.1.1.dist-info/entry_points.txt
image_generation_fastmcp_server-0.1.1.dist-info/licenses/LICENSE
image_generation_fastmcp_server-0.1.1.dist-info/RECORD
